odoo8_addon_l10n_it_fatturapa_pec-8.0.2.0.0-nspkg.pth
odoo_addons/l10n_it_fatturapa_pec/README.rst
odoo_addons/l10n_it_fatturapa_pec/__init__.py
odoo_addons/l10n_it_fatturapa_pec/__openerp__.py
odoo_addons/l10n_it_fatturapa_pec/data/fetchmail_data.xml
odoo_addons/l10n_it_fatturapa_pec/i18n/l10n_it_fatturapa_pec.pot
odoo_addons/l10n_it_fatturapa_pec/models/__init__.py
odoo_addons/l10n_it_fatturapa_pec/models/account.py
odoo_addons/l10n_it_fatturapa_pec/models/company.py
odoo_addons/l10n_it_fatturapa_pec/models/fatturapa_attachment_out.py
odoo_addons/l10n_it_fatturapa_pec/models/fetchmail.py
odoo_addons/l10n_it_fatturapa_pec/models/mail_thread.py
odoo_addons/l10n_it_fatturapa_pec/readme/CONFIGURE.rst
odoo_addons/l10n_it_fatturapa_pec/readme/CONTRIBUTORS.rst
odoo_addons/l10n_it_fatturapa_pec/readme/DESCRIPTION.rst
odoo_addons/l10n_it_fatturapa_pec/readme/USAGE.rst
odoo_addons/l10n_it_fatturapa_pec/security/groups.xml
odoo_addons/l10n_it_fatturapa_pec/security/ir.model.access.csv
odoo_addons/l10n_it_fatturapa_pec/static/description/icon.png
odoo_addons/l10n_it_fatturapa_pec/static/description/index.html
odoo_addons/l10n_it_fatturapa_pec/tests/__init__.py
odoo_addons/l10n_it_fatturapa_pec/tests/e_invoice_common.py
odoo_addons/l10n_it_fatturapa_pec/tests/test_e_invoice_common.py
odoo_addons/l10n_it_fatturapa_pec/tests/test_e_invoice_response.py
odoo_addons/l10n_it_fatturapa_pec/tests/test_e_invoice_send.py
odoo_addons/l10n_it_fatturapa_pec/tests/data/ACCETTAZIONE_ IT03339130126_00009.xml.txt
odoo_addons/l10n_it_fatturapa_pec/tests/data/CONSEGNA_ IT03339130126_00009.xml.txt
odoo_addons/l10n_it_fatturapa_pec/tests/data/POSTA CERTIFICATA: Invio File 7339338 (broken XML).txt
odoo_addons/l10n_it_fatturapa_pec/tests/data/POSTA CERTIFICATA: Invio File 7339338.txt
odoo_addons/l10n_it_fatturapa_pec/tests/data/POSTA CERTIFICATA_ Ricevuta di consegna 6782414.txt
odoo_addons/l10n_it_fatturapa_pec/views/account.xml
odoo_addons/l10n_it_fatturapa_pec/views/company_view.xml
odoo8_addon_l10n_it_fatturapa_pec-8.0.2.0.0.dist-info/METADATA
odoo8_addon_l10n_it_fatturapa_pec-8.0.2.0.0.dist-info/WHEEL
odoo8_addon_l10n_it_fatturapa_pec-8.0.2.0.0.dist-info/namespace_packages.txt
odoo8_addon_l10n_it_fatturapa_pec-8.0.2.0.0.dist-info/top_level.txt
odoo8_addon_l10n_it_fatturapa_pec-8.0.2.0.0.dist-info/RECORD
