Metadata-Version: 2.1
Name: odoo8-addon-l10n-it-fatturapa-pec
Version: 8.0.2.0.0
Summary: Send electronic invoices via PEC
Home-page: https://github.com/OCA/l10n-italy
Author: Openforce Srls Unipersonale, Odoo Community Association (OCA)
Author-email: support@odoo-community.org
License: AGPL-3
Platform: UNKNOWN
Classifier: Programming Language :: Python
Classifier: Framework :: Odoo
Classifier: License :: OSI Approved :: GNU Affero General Public License v3
Requires-Python: ~=2.7
Requires-Dist: odoo8-addon-l10n-it-fatturapa-in
Requires-Dist: odoo8-addon-l10n-it-fatturapa-out
Requires-Dist: odoo8-addon-l10n-it-sdi-channel
Requires-Dist: odoo (<9.0a,>=8.0a)
